peace_augmentation/__init__.py
peace_augmentation/easy_data_augmentation.py
peace_augmentation/replace_named_entities.py
peace_augmentation/utils.py
peace_augmentation/words_lists/__init__.py
peace_augmentation/words_lists/entities_list.json
peace_augmentation/words_lists/scalarity.json
peace_augmentation/words_lists/special_tokens.json
peace_augmentation/words_lists/speculative.json
peace_augmentation-0.1.5.dist-info/licenses/LICENSE
peace_augmentation-0.1.5.dist-info/METADATA
peace_augmentation-0.1.5.dist-info/WHEEL
peace_augmentation-0.1.5.dist-info/top_level.txt
peace_augmentation-0.1.5.dist-info/RECORD
